umi/__init__.py
umi/common.py
umi/adapters/__init__.py
umi/adapters/common.py
umi/adapters/axil2umi/axil2umi.py
umi/adapters/axil2umi/rtl/axil2umi.v
umi/adapters/include/tl-uh.vh
umi/adapters/rtl/README.md
umi/adapters/rtl/umi_address_remap.v
umi/adapters/rtl/umi_packet_merge_greedy.v
umi/adapters/testbench/buffer.memh
umi/adapters/testbench/buffer_axilite.memh
umi/adapters/testbench/config.h
umi/adapters/testbench/config.vlt
umi/adapters/testbench/tb_axilite2umi.v
umi/adapters/testbench/tb_tl2umi_np.v
umi/adapters/testbench/tb_umi_data_aggregator.v
umi/adapters/testbench/test_tl2umi_np.py
umi/adapters/testbench/test_umi2apb.py
umi/adapters/testbench/test_umi2axilite.py
umi/adapters/testbench/test_umi2tl_np.py
umi/adapters/testbench/test_umi_address_remap.py
umi/adapters/testbench/test_umi_packet_merge_greedy.py
umi/adapters/testbench/testbench_umi2apb.sv
umi/adapters/testbench/testbench_umi2axilite.sv
umi/adapters/testbench/testbench_umi2tl_np.cc
umi/adapters/testbench/testbench_umi2tl_np.v
umi/adapters/testbench/testbench_umi_address_remap.v
umi/adapters/testbench/testbench_umi_packet_merge_greedy.cc
umi/adapters/testbench/testbench_umi_packet_merge_greedy.v
umi/adapters/testbench/tilelink.h
umi/adapters/testbench/tlmemsim.cpp
umi/adapters/testbench/tlmemsim.h
umi/adapters/tl2umi/tl2umi.py
umi/adapters/tl2umi/rtl/tl2umi.v
umi/adapters/tl2umi/rtl/umi_data_aggregator.v
umi/adapters/umi2apb/umi2apb.py
umi/adapters/umi2apb/rtl/umi2apb.v
umi/adapters/umi2axil/umi2axil.py
umi/adapters/umi2axil/rtl/umi2axil.v
umi/adapters/umi2tl/umi2tl.py
umi/adapters/umi2tl/rtl/umi2tl.v
umi/lumi/README.md
umi/lumi/__init__.py
umi/lumi/lumi.py
umi/lumi/rtl/lumi.v
umi/lumi/rtl/lumi_crossbar.v
umi/lumi/rtl/lumi_regmap.vh
umi/lumi/rtl/lumi_regs.v
umi/lumi/rtl/lumi_rx.v
umi/lumi/rtl/lumi_rx_ready.v
umi/lumi/rtl/lumi_tx.v
umi/lumi/rtl/lumi_tx_ready.v
umi/lumi/testbench/config.vlt
umi/lumi/testbench/testbench_lumi.sv
umi/lumi/testbench/testbench_lumi_ready.sv
umi/sumi/__init__.py
umi-0.4.2.dist-info/licenses/AUTHORS
umi-0.4.2.dist-info/licenses/LICENSE
umi-0.4.2.dist-info/METADATA
umi-0.4.2.dist-info/WHEEL
umi-0.4.2.dist-info/top_level.txt
umi-0.4.2.dist-info/RECORD
