Metadata-Version: 2.4
Name: umi
Version: 0.4.2
Summary: Universal Memory Interface (UMI)
Author: Zero ASIC
License:                                  Apache License
Project-URL: Homepage, https://github.com/zeroasiccorp/umi
Requires-Python: >=3.9
License-File: LICENSE
License-File: AUTHORS
Requires-Dist: siliconcompiler>=0.35.0
Requires-Dist: lambdalib<0.10.0,>=0.4.0
Provides-Extra: test
Requires-Dist: pytest==8.4.2; extra == "test"
Requires-Dist: pytest-xdist==3.8.0; extra == "test"
Requires-Dist: pytest-timeout==2.4.0; extra == "test"
Requires-Dist: flake8==7.3.0; extra == "test"
Requires-Dist: switchboard-hw==0.3.0; extra == "test"
Dynamic: license-file
